odoo10_addon_product_code_unique-10.0.1.0.0.99.dev1-py2.7-nspkg.pth
odoo/addons/product_code_unique/README.rst
odoo/addons/product_code_unique/__init__.py
odoo/addons/product_code_unique/__manifest__.py
odoo/addons/product_code_unique/hooks.py
odoo/addons/product_code_unique/i18n/product_code_unique.pot
odoo/addons/product_code_unique/models/__init__.py
odoo/addons/product_code_unique/models/product.py
odoo/addons/product_code_unique/static/description/icon.png
odoo10_addon_product_code_unique-10.0.1.0.0.99.dev1.dist-info/METADATA
odoo10_addon_product_code_unique-10.0.1.0.0.99.dev1.dist-info/RECORD
odoo10_addon_product_code_unique-10.0.1.0.0.99.dev1.dist-info/WHEEL
odoo10_addon_product_code_unique-10.0.1.0.0.99.dev1.dist-info/namespace_packages.txt
odoo10_addon_product_code_unique-10.0.1.0.0.99.dev1.dist-info/top_level.txt
